alpha_shapes/__init__.py
alpha_shapes/alpha_shapes.py
alpha_shapes/boundary.py
alpha_shapes/plotting.py
alpha_shapes-1.1.0.dist-info/LICENSE
alpha_shapes-1.1.0.dist-info/METADATA
alpha_shapes-1.1.0.dist-info/WHEEL
alpha_shapes-1.1.0.dist-info/top_level.txt
alpha_shapes-1.1.0.dist-info/RECORD
