Metadata-Version: 2.1
Name: alpha-shapes
Version: 1.1.0
Summary: reconstruct the shape of a 2D point cloud.
Home-page: https://github.com/panosz/alpha_shapes
Author: Panagiotis Zestanakis
Author-email: panosz@gmail.com
Classifier: Programming Language :: Python :: 3
Classifier: License :: OSI Approved :: MIT License
Classifier: Operating System :: OS Independent
Classifier: Development Status :: 3 - Alpha
Classifier: Intended Audience :: Science/Research
Classifier: Topic :: Scientific/Engineering
Classifier: Topic :: Scientific/Engineering :: Information Analysis
Requires-Python: >=3.8
License-File: LICENSE
Requires-Dist: numpy
Requires-Dist: shapely
Requires-Dist: matplotlib
